rednote/.env
rednote/1.py
rednote/__init__.py
rednote/__main__.py
rednote/__main__stream__voice.py
rednote/__main__voice__.py
rednote/__main__voice_converstation.py
rednote/__main__voice_mavis.py
rednote/generate.py
rednote/prompt.py
rednote/simplex_websocket_demo.py
rednote/stream.wav
rednote/streaming_asr_demo.py
rednote/test.py
rednote/tts_http_voice.py
rednote-0.1.1.dist-info/METADATA
rednote-0.1.1.dist-info/WHEEL
rednote-0.1.1.dist-info/entry_points.txt
rednote-0.1.1.dist-info/RECORD
