Metadata-Version: 2.3
Name: rednote
Version: 0.1.1
Summary: 
Author: mavisli002
Author-email: lifunnypets@gmail.com
Requires-Python: >=3.12
Classifier: Programming Language :: Python :: 3
Classifier: Programming Language :: Python :: 3.12
Classifier: Programming Language :: Python :: 3.13
Requires-Dist: aiofiles (>=24.1.0,<25.0.0)
Requires-Dist: openai (>=1.73.0,<2.0.0)
Requires-Dist: playsound (==1.2.2)
Requires-Dist: pygame (>=2.6.1,<3.0.0)
Requires-Dist: python-dotenv (>=1.1.0,<2.0.0)
Requires-Dist: requests (>=2.32.3,<3.0.0)
Requires-Dist: sounddevice (>=0.5.1,<0.6.0)
Requires-Dist: soundfile (>=0.13.1,<0.14.0)
Requires-Dist: websockets (>=15.0.1,<16.0.0)
